[
  {
    "tag": "nav",
    "count": 1,
    "classes": [
      "bg-[#3d378e] hidden sm:block"
    ]
  },
  {
    "tag": "main",
    "count": 1,
    "classes": [
      "pt-16 sm:pt-[116px]"
    ]
  },
  {
    "tag": "footer",
    "count": 1,
    "classes": [
      "bg-[#3d378e] text-gray-300"
    ]
  },
  {
    "tag": "section",
    "count": 2,
    "classes": [
      "scroll-mt-32",
      "mt-5"
    ]
  },
  {
    "tag": "h1",
    "count": 0,
    "classes": []
  },
  {
    "tag": "h2",
    "count": 2,
    "classes": [
      "border-b font-semibold pb-2 text-lg",
      "font-semibold md:text-[1.8rem] text-[#3d378e] text-[1.55rem] tracking-[-0.02em]"
    ]
  }
]